LICENSE
MANIFEST.in
README.rst
requirements.txt
setup.cfg
setup.py
modoboa_admin/__init__.py
modoboa_admin/app_settings.py
modoboa_admin/factories.py
modoboa_admin/lib.py
modoboa_admin/modo_extension.py
modoboa_admin/postfix_maps.py
modoboa_admin/signals.py
modoboa_admin/urls.py
modoboa_admin.egg-info/PKG-INFO
modoboa_admin.egg-info/SOURCES.txt
modoboa_admin.egg-info/dependency_links.txt
modoboa_admin.egg-info/not-zip-safe
modoboa_admin.egg-info/requires.txt
modoboa_admin.egg-info/top_level.txt
modoboa_admin/forms/__init__.py
modoboa_admin/forms/account.py
modoboa_admin/forms/alias.py
modoboa_admin/forms/domain.py
modoboa_admin/forms/export.py
modoboa_admin/forms/forward.py
modoboa_admin/forms/import_.py
modoboa_admin/locale/cs_CZ/LC_MESSAGES/django.mo
modoboa_admin/locale/cs_CZ/LC_MESSAGES/django.po
modoboa_admin/locale/cs_CZ/LC_MESSAGES/djangojs.mo
modoboa_admin/locale/cs_CZ/LC_MESSAGES/djangojs.po
modoboa_admin/locale/de/LC_MESSAGES/django.mo
modoboa_admin/locale/de/LC_MESSAGES/django.po
modoboa_admin/locale/de/LC_MESSAGES/djangojs.mo
modoboa_admin/locale/de/LC_MESSAGES/djangojs.po
modoboa_admin/locale/en/LC_MESSAGES/django.mo
modoboa_admin/locale/en/LC_MESSAGES/django.po
modoboa_admin/locale/en/LC_MESSAGES/djangojs.mo
modoboa_admin/locale/en/LC_MESSAGES/djangojs.po
modoboa_admin/locale/es/LC_MESSAGES/django.mo
modoboa_admin/locale/es/LC_MESSAGES/django.po
modoboa_admin/locale/es/LC_MESSAGES/djangojs.mo
modoboa_admin/locale/es/LC_MESSAGES/djangojs.po
modoboa_admin/locale/fr/LC_MESSAGES/django.mo
modoboa_admin/locale/fr/LC_MESSAGES/django.po
modoboa_admin/locale/fr/LC_MESSAGES/djangojs.mo
modoboa_admin/locale/fr/LC_MESSAGES/djangojs.po
modoboa_admin/locale/it/LC_MESSAGES/django.mo
modoboa_admin/locale/it/LC_MESSAGES/django.po
modoboa_admin/locale/it/LC_MESSAGES/djangojs.mo
modoboa_admin/locale/it/LC_MESSAGES/djangojs.po
modoboa_admin/locale/nl_NL/LC_MESSAGES/django.mo
modoboa_admin/locale/nl_NL/LC_MESSAGES/django.po
modoboa_admin/locale/nl_NL/LC_MESSAGES/djangojs.mo
modoboa_admin/locale/nl_NL/LC_MESSAGES/djangojs.po
modoboa_admin/locale/pt_BR/LC_MESSAGES/django.mo
modoboa_admin/locale/pt_BR/LC_MESSAGES/django.po
modoboa_admin/locale/pt_BR/LC_MESSAGES/djangojs.mo
